polyglotlm/__init__.py
polyglotlm/models.py
polyglotlm/providers/__init__.py
polyglotlm/providers/aws_bedrock_provider.py
polyglotlm/providers/base_provider.py
polyglotlm/providers/factory.py
polyglotlm/providers/openai_provider.py
polyglotlm/providers/vertex_ai_text_provider.py
polyglotlm/streamed_completion.py
polyglotlm/utils/__init__.py
polyglotlm/utils/logs.py
polyglotlm/utils/tokens.py
polyglotlm/xperiments/exp_multi.py
polyglotlm-0.1.9.dist-info/LICENSE
polyglotlm-0.1.9.dist-info/METADATA
polyglotlm-0.1.9.dist-info/WHEEL
polyglotlm-0.1.9.dist-info/RECORD
