Metadata-Version: 2.1
Name: polyglotlm
Version: 0.1.9
Summary: 
Author: Laurentiu Piciu
Author-email: laurentiupiciu@gmail.com
Requires-Python: >=3.10,<4.0
Classifier: Programming Language :: Python :: 3
Classifier: Programming Language :: Python :: 3.10
Classifier: Programming Language :: Python :: 3.11
Classifier: Programming Language :: Python :: 3.12
Requires-Dist: boto3 (>=1.28.79,<2.0.0)
Requires-Dist: botocore (>=1.31.79,<2.0.0)
Requires-Dist: google-cloud-aiplatform (>=1.36.0,<2.0.0)
Requires-Dist: openai (>=1.1.1,<2.0.0)
Requires-Dist: pydantic (>=2.4.2,<3.0.0)
Requires-Dist: python-decouple (>=3.8,<4.0)
Requires-Dist: requests (>=2.31.0,<3.0.0)
Requires-Dist: tenacity (>=8.0,<9.0)
Requires-Dist: tiktoken (>=0.5.1,<0.6.0)
